chartscrapper/__init__.py
chartscrapper/main.py
chartscrapper-0.4.dist-info/METADATA
chartscrapper-0.4.dist-info/WHEEL
chartscrapper-0.4.dist-info/entry_points.txt
chartscrapper-0.4.dist-info/top_level.txt
chartscrapper-0.4.dist-info/RECORD
