Metadata-Version: 2.1
Name: chartscrapper
Version: 0.4
Requires-Dist: selenium
